makereq.py
makereq-0.1.1.dist-info/METADATA
makereq-0.1.1.dist-info/WHEEL
makereq-0.1.1.dist-info/entry_points.txt
makereq-0.1.1.dist-info/top_level.txt
makereq-0.1.1.dist-info/RECORD
